{
  "export_timestamp": "2025-07-25T18:25:52.696087",
  "exported_by_admin": "sahilsaurav2507@gmail.com",
  "total_users_exported": 8,
  "note": "Feedback data is preserved in the database with user_id set to NULL",
  "users": [
    {
      "id": 47,
      "name": "Prabhjot Jaswal",
      "email": "prabhjotjaswal09@gmail.com",
      "total_points": 0,
      "shares_count": 0,
      "default_rank": 1,
      "current_rank": 1,
      "is_active": true,
      "created_at": "2025-07-25T17:55:03",
      "updated_at": "2025-07-25T23:25:03",
      "share_events": [],
      "feedback_responses": []
    },
    {
      "id": 48,
      "name": "Sahil Saurav",
      "email": "sahilsaurav250e7@gmail.com",
      "total_points": 0,
      "shares_count": 0,
      "default_rank": 2,
      "current_rank": 2,
      "is_active": true,
      "created_at": "2025-07-25T17:58:12",
      "updated_at": "2025-07-25T23:28:11",
      "share_events": [],
      "feedback_responses": []
    },
    {
      "id": 49,
      "name": "Welcome Test User 1",
      "email": "welcome1@test.com",
      "total_points": 0,
      "shares_count": 0,
      "default_rank": 3,
      "current_rank": 3,
      "is_active": true,
      "created_at": "2025-07-25T18:11:49",
      "updated_at": "2025-07-25T23:41:49",
      "share_events": [],
      "feedback_responses": []
    },
    {
      "id": 50,
      "name": "Welcome Test User 2",
      "email": "welcome2@test.com",
      "total_points": 0,
      "shares_count": 0,
      "default_rank": 4,
      "current_rank": 4,
      "is_active": true,
      "created_at": "2025-07-25T18:11:49",
      "updated_at": "2025-07-25T23:41:49",
      "share_events": [],
      "feedback_responses": []
    },
    {
      "id": 51,
      "name": "Welcome Test User 3",
      "email": "welcome3@test.com",
      "total_points": 0,
      "shares_count": 0,
      "default_rank": 5,
      "current_rank": 5,
      "is_active": true,
      "created_at": "2025-07-25T18:11:50",
      "updated_at": "2025-07-25T23:41:49",
      "share_events": [],
      "feedback_responses": []
    },
    {
      "id": 54,
      "name": "Critical Fix Test User",
      "email": "criticalfix@test.com",
      "total_points": 0,
      "shares_count": 0,
      "default_rank": 6,
      "current_rank": 6,
      "is_active": true,
      "created_at": "2025-07-25T18:14:29",
      "updated_at": "2025-07-25T23:44:28",
      "share_events": [],
      "feedback_responses": []
    },
    {
      "id": 55,
      "name": "Prabhjot Jaswal",
      "email": "prabhjotjaswal11@gmail.com",
      "total_points": 0,
      "shares_count": 0,
      "default_rank": 7,
      "current_rank": 7,
      "is_active": true,
      "created_at": "2025-07-25T18:16:59",
      "updated_at": "2025-07-25T23:46:59",
      "share_events": [],
      "feedback_responses": []
    },
    {
      "id": 56,
      "name": "Test Queue User",
      "email": "testqueue@example.com",
      "total_points": 0,
      "shares_count": 0,
      "default_rank": 8,
      "current_rank": 8,
      "is_active": true,
      "created_at": "2025-07-25T18:21:45",
      "updated_at": "2025-07-25T23:51:44",
      "share_events": [],
      "feedback_responses": []
    }
  ]
}